README.rst
setup.cfg
setup.py
phonet/Phonological.py
phonet/__init__.py
phonet/example.py
phonet/phonet.py
phonet.egg-info/PKG-INFO
phonet.egg-info/SOURCES.txt
phonet.egg-info/dependency_links.txt
phonet.egg-info/requires.txt
phonet.egg-info/top_level.txt
phonet/audios/pataka.wav
phonet/audios/sentence.wav
phonet/models/model.h5
phonet/models/model.json
phonet/models/mu.npy
phonet/models/phonemes.hdf5
phonet/models/std.npy