Metadata-Version: 1.1
Name: phonet
Version: 0.3.5
Summary: Compute phonological posteriors from speech signals using a deep learning scheme
Home-page: https://github.com/jcvasquezc/phonet
Author: J. C. Vasquez-Correa
Author-email: juan.vasquez@fau.de
License: MIT
Download-URL: https://github.com/jcvasquezc/phonet/archive/0.3.5.tar.gz
Keywords: phonological,speech,speech features,articulatory features,phoneme recognition
Platform: UNKNOWN
Classifier: Development Status :: 4 - Beta
Classifier: Intended Audience :: Developers
Classifier: Topic :: Software Development :: Build Tools
Classifier: License :: OSI Approved :: MIT License
Classifier: Programming Language :: Python :: 3
Classifier: Programming Language :: Python :: 3.4
Classifier: Programming Language :: Python :: 3.5
Classifier: Programming Language :: Python :: 3.6
